pyarraytools/__init__.py
pyarraytools/core.py
pyarraytools-0.1.0.dist-info/METADATA
pyarraytools-0.1.0.dist-info/WHEEL
pyarraytools-0.1.0.dist-info/top_level.txt
pyarraytools-0.1.0.dist-info/RECORD
