Metadata-Version: 2.4
Name: pyarraytools
Version: 0.1.0
Summary: Flatten, chunk, deduplicate, rotate, shuffle, and group lists
Author: PyLib Contributors
License: MIT
Keywords: array,list,utilities,data-structures
Classifier: Development Status :: 3 - Alpha
Classifier: Intended Audience :: Developers
Classifier: License :: OSI Approved :: MIT License
Classifier: Programming Language :: Python :: 3
Requires-Python: >=3.8
